mysql_fastconnector/__init__.py
mysql_fastconnector/app.py
mysql_fastconnector/main.py
mysql_fastconnector-0.0.7.dist-info/LICENSE
mysql_fastconnector-0.0.7.dist-info/METADATA
mysql_fastconnector-0.0.7.dist-info/WHEEL
mysql_fastconnector-0.0.7.dist-info/top_level.txt
mysql_fastconnector-0.0.7.dist-info/RECORD
