Metadata-Version: 2.1
Name: mysql-fastconnector
Version: 0.0.7
Summary: it helps to connect mysql and do CURD action easily 
Home-page: https://github.com/ilayaraja1984/mysqleasyquery
Author: ilayaraja
Author-email: ilayaraja.python@gmail.com
Project-URL: Bug Tracker, https://github.com/ilayaraja1984/mysqleasyquery/issues
Classifier: Programming Language :: Python :: 3
Classifier: License :: OSI Approved :: MIT License
Classifier: Operating System :: OS Independent
Requires-Python: >=3.6
License-File: LICENSE
Requires-Dist: mysql-connector-python ==8.1.0
Requires-Dist: mysqlclient ==2.0.3
